hcga/__init__.py
hcga/analysis.py
hcga/app.py
hcga/extraction.py
hcga/feature_class.py
hcga/graph.py
hcga/hcga.py
hcga/io.py
hcga/plotting.py
hcga/utils.py
hcga/dataset_creation/__init__.py
hcga/dataset_creation/benchmark_datasets.py
hcga/dataset_creation/synthetic_datasets.py
hcga/dataset_creation/test_dataset.py
hcga/features/__init__.py
hcga/features/assortativity.py
hcga/features/basal_nodes.py
hcga/features/basic_stats.py
hcga/features/centralities_basic.py
hcga/features/chemical_theory.py
hcga/features/cliques.py
hcga/features/clustering.py
hcga/features/communities_asyn.py
hcga/features/communities_bisection.py
hcga/features/communities_labelprop.py
hcga/features/communities_modularity.py
hcga/features/components.py
hcga/features/connectance.py
hcga/features/core_number.py
hcga/features/covering.py
hcga/features/cycle_basis.py
hcga/features/distance_measures.py
hcga/features/dominating_sets.py
hcga/features/efficiency.py
hcga/features/eulerian.py
hcga/features/flow_hierarchy.py
hcga/features/in_out_degrees.py
hcga/features/independent_sets.py
hcga/features/jaccard_similarity.py
hcga/features/k_components.py
hcga/features/link_analysis_hits.py
hcga/features/looplessness.py
hcga/features/maximal_matching.py
hcga/features/minimum_cuts.py
hcga/features/nestedness.py
hcga/features/node_clique_number.py
hcga/features/node_connectivity.py
hcga/features/node_features.py
hcga/features/rbc.py
hcga/features/reciprocity.py
hcga/features/rich_club.py
hcga/features/scale_free.py
hcga/features/shortest_paths.py
hcga/features/simple_cycles.py
hcga/features/small_worldness.py
hcga/features/spectrum.py
hcga/features/structural_holes.py
hcga/features/utils.py
hcga/features/vitality.py
hcga-1.0.2.dist-info/LICENSE
hcga-1.0.2.dist-info/METADATA
hcga-1.0.2.dist-info/WHEEL
hcga-1.0.2.dist-info/entry_points.txt
hcga-1.0.2.dist-info/top_level.txt
hcga-1.0.2.dist-info/RECORD
