Metadata-Version: 2.1
Name: hcga
Version: 1.0.2
Summary: Highly comparative graph analysis
Home-page: UNKNOWN
Author: Robert Peach + Alexis Arnaudon + Henry Palasciano
Author-email: r.peach13@imperial.ac.uk
License: UNKNOWN
Platform: UNKNOWN
License-File: LICENSE
Requires-Dist: click (>=7.1.1)
Requires-Dist: numpy (>=1.18.2)
Requires-Dist: scipy (>=1.4.1)
Requires-Dist: tqdm (>=4.45.0)
Requires-Dist: networkx (>=2.4)
Requires-Dist: scikit-learn (>=0.23.1)
Requires-Dist: matplotlib (>=1.4.3)
Requires-Dist: seaborn (>=0.9.0)
Requires-Dist: shap (>=0.35.0)
Requires-Dist: pandas (>=1.0.3)
Requires-Dist: wget (>=3.2)
Requires-Dist: sympy (>=1.4)
Requires-Dist: joblib (>=0.14.1)
Requires-Dist: IPython (>=7.19.0)
Requires-Dist: xgboost (>=1.3.3)
